tledger_plugin_gamesdk/__init__.py
tledger_plugin_gamesdk/tLedger_models.py
tledger_plugin_gamesdk/tLedger_plugin.py
tledger_plugin_gamesdk-0.1.2.dist-info/METADATA
tledger_plugin_gamesdk-0.1.2.dist-info/WHEEL
tledger_plugin_gamesdk-0.1.2.dist-info/RECORD
