Metadata-Version: 2.4
Name: tledger_plugin_gamesdk
Version: 0.1.2
Summary: TLedger SDK for GAME by Virtuals
Project-URL: Homepage, https://github.com/game-by-virtuals/game-python/plugins/tLedger
Project-URL: Bug Tracker, https://github.com/game-by-virtuals/game-python
Author-email: Prateek Tiwari <ptiwari@t54.ai>, Akshit Arora <aarora@t54.ai>
Classifier: Development Status :: 3 - Alpha
Classifier: Intended Audience :: Developers
Classifier: License :: OSI Approved :: MIT License
Classifier: Operating System :: OS Independent
Classifier: Programming Language :: Python :: 3
Classifier: Programming Language :: Python :: 3.8
Classifier: Programming Language :: Python :: 3.9
Classifier: Programming Language :: Python :: 3.10
Classifier: Programming Language :: Python :: 3.11
Classifier: Topic :: Software Development :: Libraries :: Python Modules
Requires-Python: >=3.8
Requires-Dist: aiohttp>=3.11.11
Requires-Dist: game-sdk>=0.1.1
